<?xml version="1.0" encoding="UTF-8"?>
<fd:form xmlns:fd="http://apache.org/cocoon/forms/1.0#definition">
    <fd:widgets>
        <fd:field id="deals_username" required="true" >
            <fd:label><i18n:text>deals.authentication.username</i18n:text></fd:label>
            <fd:datatype base="string"/>
            <!-- <fd:on-value-changed>
              <java ref="authenticationEvent"/>
            </fd:on-value-changed> -->
        </fd:field>
        <fd:field id="deals_password" required="true" >
            <fd:label><i18n:text>deals.authentication.password</i18n:text></fd:label>
            <fd:datatype base="string"/>
              <!-- <fd:validation >
                <fd:java ref="authenticationValidator"/>
              </fd:validation>-->
        </fd:field>
        <fd:submit id="dealsenter" validate="true">
            <fd:label><i18n:text>deals.authentication.enter</i18n:text></fd:label>
          <!--   <fd:on-action>
                <javascript>
                </javascript>
            </fd:on-action> -->
        </fd:submit>
    </fd:widgets>
</fd:form>